{
    "labels": {
        "20231001": "2023-10-01 (Classic 1.0, release I, Launch)",
        "20231008": "2023-10-08 (classic 1.0, patch II)",
        "20231014": "2023-10-14 (Classic 1.0, patch III)",
        "20231104": "2023-11-04 (Classic 1.0, patch IV)",
        "20231129": "2023-11-29 (Classic 1.0, patch V)",
        "20231213": "2023-12-13 (Classic 1.0, patch VI)",
        "20231226": "2023-12-26 (Classic 1.3, release I, Temple SolRo/Classic Planes)",
        "20240118": "2024-01-18 (Classic 1.3, patch II)",
        "20240213": "2024-02-13 (Classic 1.3, patch III)",
        "20240317": "2024-03-17 (Classic 1.6, release I, The Hole)",
        "20240415": "2024-04-15 (Classic 1.6, patch II)",
        "20240529": "2024-05-29 (Classic 1.9, release I, Early Access Kunark)",
        "20240618": "2024-06-18 (Classic 1.9, patch II, latest)",
        "20240701": "2024-07-01 (Kunark 2.0, release I)"
    },
    "diffs": {
        "releases": [
            "20231001-20240618",
            "20231226-20240317",
            "20240317-20240529",
            "20240529-20240701"
        ],
        "sequential": [
            "20231226-20240118",
            "20240118-20240213",
            "20240213-20240317",
            "20240317-20240415",
            "20240415-20240529",
            "20240529-20240618",
            "20240618-20240701"
        ]
    }
}